{"hash":"64a9e8afa68c1466f7ef441294c96aecf9a68066","data":{"article":{"id":"a41c2e6fd4247251fa87a9b65c1dce4f","title":"Variant Calling with Galaxy & the GVL for beginners","tease":"from Melbourne Bioinformatics","category":"events","date":"2018-03-21","days":1,"contact":"Christina Hall","contact_url":"","authors":"","location":"Melbourne Bioinformatics, Carlton, Victoria, Australia","location_url":"https://www.melbournebioinformatics.org.au/training-and-events/","source_blog":"","source_blog_url":"","skip_title_render":null,"links":[],"image":"","images":{},"external_url":"https://www.melbournebioinformatics.org.au/training-events/variant-calling-galaxy-gvl/#more-1012","content":"\n"}},"context":{}}