{"hash":"ef8aba8bb8a02457efb168ecda8caf9311205534","data":{"article":{"id":"ed9a0582a27b80c5bd099423e00c59d2","title":"","tease":"","category":null,"date":null,"days":null,"contact":"","contact_url":"","authors":"","location":"","location_url":"","source_blog":"","source_blog_url":"","skip_title_render":null,"redirect":"","links":[],"image":"","images":{},"external_url":"","content":"<p>Galaxy provides tools for extracting subsets of genomic sequences and alignments. Currently the public instance of Galaxy supports the following sequences and alignments</p>\n<p>28 sequences are available in Galaxy (not including <a href=\"/main/data-libraries/microbes/\">Main/DataLibraries/Microbes</a>):</p>\n<table>\n  <tr>\n    <td> <strong>Build</strong></td>\n    <td> <strong>Species</strong></td>\n    <td> <strong>Clade</strong></td>\n  </tr>\n  <tr>\n    <td> anoGam1</td>\n    <td> A. gambiae</td>\n    <td> Insect</td>\n  </tr>\n  <tr>\n    <td> bosTau2</td>\n    <td> Cow</td>\n    <td> Vertebrate</td>\n  </tr>\n  <tr>\n    <td> canFam1</td>\n    <td> Dog</td>\n    <td> Vertebrate</td>\n  </tr>\n  <tr>\n    <td> canFam2</td>\n    <td> Dog</td>\n    <td> Vertebrate</td>\n  </tr>\n  <tr>\n    <td> ce2</td>\n    <td> C. elegans</td>\n    <td> Nematode</td>\n  </tr>\n  <tr>\n    <td> danRer2</td>\n    <td> Zebrafish</td>\n    <td> Vertebrate</td>\n  </tr>\n  <tr>\n    <td> danRer3</td>\n    <td> Zebrafish</td>\n    <td> Vertebrate</td>\n  </tr>\n  <tr>\n    <td> danRer4</td>\n    <td> Zebrafish</td>\n    <td> Vertebrate</td>\n  </tr>\n  <tr>\n    <td> dm2</td>\n    <td> D. melanogaster</td>\n    <td> Insect</td>\n  </tr>\n  <tr>\n    <td> dp3</td>\n    <td> D. pseudoobscura</td>\n    <td> Insect</td>\n  </tr>\n  <tr>\n    <td> droSim1</td>\n    <td> D. simulans</td>\n    <td> Insect</td>\n  </tr>\n  <tr>\n    <td> droYak2</td>\n    <td> D. yakuba</td>\n    <td> Insect</td>\n  </tr>\n  <tr>\n    <td> fr1</td>\n    <td> Fugu</td>\n    <td> Vertebrate</td>\n  </tr>\n  <tr>\n    <td> galGal2</td>\n    <td> Chicken</td>\n    <td> Vertebrate</td>\n  </tr>\n  <tr>\n    <td> hg16</td>\n    <td> Human</td>\n    <td> Vertebrate</td>\n  </tr>\n  <tr>\n    <td> hg17</td>\n    <td> Human</td>\n    <td> Vertebrate</td>\n  </tr>\n  <tr>\n    <td> hg18</td>\n    <td> Human</td>\n    <td> Vertebrate</td>\n  </tr>\n  <tr>\n    <td> musMus6</td>\n    <td> Mouse</td>\n    <td> Vertebrate</td>\n  </tr>\n  <tr>\n    <td> musMus7</td>\n    <td> Mouse</td>\n    <td> Vertebrate</td>\n  </tr>\n  <tr>\n    <td> musMus8</td>\n    <td> Mouse</td>\n    <td> Vertebrate</td>\n  </tr>\n  <tr>\n    <td> monDom4</td>\n    <td> Opossum</td>\n    <td> Vertebrate</td>\n  </tr>\n  <tr>\n    <td> panTro1</td>\n    <td> Chimpanzee</td>\n    <td> Vertebrate</td>\n  </tr>\n  <tr>\n    <td> panTro2</td>\n    <td> Chimpanzee</td>\n    <td> Vertebrate</td>\n  </tr>\n  <tr>\n    <td> rheMac2</td>\n    <td> Rhesus</td>\n    <td> Vertebrate</td>\n  </tr>\n  <tr>\n    <td> ratNor3</td>\n    <td> Rat</td>\n    <td> Vertebrate</td>\n  </tr>\n  <tr>\n    <td> ratNor4</td>\n    <td> Rat</td>\n    <td> Vertebrate</td>\n  </tr>\n  <tr>\n    <td> sacCer1</td>\n    <td> Yeast (S. cerevisiae)</td>\n    <td> Other</td>\n  </tr>\n  <tr>\n    <td> tetNig1</td>\n    <td> Tetraodon</td>\n    <td> Vertebrate</td>\n  </tr>\n</table>\n<p>156 pairwise alignments are available in Galaxy:</p>\n<table>\n  <tr>\n    <td> <strong>Build</strong></td>\n    <td> <strong>Aligned with</strong></td>\n  </tr>\n  <tr>\n    <td> anoGam1</td>\n    <td> dm1</td>\n  </tr>\n  <tr>\n    <td> </td>\n    <td> dm2</td>\n  </tr>\n  <tr>\n    <td> canFam1</td>\n    <td> hg17</td>\n  </tr>\n  <tr>\n    <td> </td>\n    <td> musMus6</td>\n  </tr>\n  <tr>\n    <td> canFam2</td>\n    <td> canFam2</td>\n  </tr>\n  <tr>\n    <td> </td>\n    <td> hg17</td>\n  </tr>\n  <tr>\n    <td> </td>\n    <td> hg18</td>\n  </tr>\n  <tr>\n    <td> </td>\n    <td> musMus6</td>\n  </tr>\n  <tr>\n    <td> </td>\n    <td> musMus7</td>\n  </tr>\n  <tr>\n    <td> </td>\n    <td> musMus8</td>\n  </tr>\n  <tr>\n    <td> </td>\n    <td> ratNor3</td>\n  </tr>\n  <tr>\n    <td> </td>\n    <td> ratNor4</td>\n  </tr>\n  <tr>\n    <td> danRer2</td>\n    <td> fr1</td>\n  </tr>\n  <tr>\n    <td> </td>\n    <td> hg17</td>\n  </tr>\n  <tr>\n    <td> </td>\n    <td> musMus6</td>\n  </tr>\n  <tr>\n    <td> </td>\n    <td> tetNig1</td>\n  </tr>\n  <tr>\n    <td> danRer3</td>\n    <td> fr1</td>\n  </tr>\n  <tr>\n    <td> </td>\n    <td> hg18</td>\n  </tr>\n  <tr>\n    <td> </td>\n    <td> musMus7</td>\n  </tr>\n  <tr>\n    <td> </td>\n    <td> musMus8</td>\n  </tr>\n  <tr>\n    <td> </td>\n    <td> tetNig1</td>\n  </tr>\n  <tr>\n    <td> danRer4</td>\n    <td> fr1</td>\n  </tr>\n  <tr>\n    <td> </td>\n    <td> hg18</td>\n  </tr>\n  <tr>\n    <td> </td>\n    <td> musMus8</td>\n  </tr>\n  <tr>\n    <td> </td>\n    <td> ratNor4</td>\n  </tr>\n  <tr>\n    <td> </td>\n    <td> tetNig1</td>\n  </tr>\n  <tr>\n    <td> dm2</td>\n    <td> anoGam1</td>\n  </tr>\n  <tr>\n    <td> </td>\n    <td> apiMel1</td>\n  </tr>\n  <tr>\n    <td> </td>\n    <td> apiMel2</td>\n  </tr>\n  <tr>\n    <td> </td>\n    <td> dp2</td>\n  </tr>\n  <tr>\n    <td> </td>\n    <td> dp3</td>\n  </tr>\n  <tr>\n    <td> </td>\n    <td> droAna1</td>\n  </tr>\n  <tr>\n    <td> </td>\n    <td> droMoj1</td>\n  </tr>\n  <tr>\n    <td> </td>\n    <td> droPer1</td>\n  </tr>\n  <tr>\n    <td> </td>\n    <td> droSec1</td>\n  </tr>\n  <tr>\n    <td> </td>\n    <td> droSim1</td>\n  </tr>\n  <tr>\n    <td> </td>\n    <td> droVir1</td>\n  </tr>\n  <tr>\n    <td> </td>\n    <td> droYak1</td>\n  </tr>\n  <tr>\n    <td> dp3</td>\n    <td> dm2</td>\n  </tr>\n  <tr>\n    <td> droSim1</td>\n    <td> dm2</td>\n  </tr>\n  <tr>\n    <td> droYak2</td>\n    <td> dm2</td>\n  </tr>\n  <tr>\n    <td> fr1</td>\n    <td> danRer2</td>\n  </tr>\n  <tr>\n    <td> </td>\n    <td> danRer3</td>\n  </tr>\n  <tr>\n    <td> </td>\n    <td> danRer4</td>\n  </tr>\n  <tr>\n    <td> </td>\n    <td> hg18</td>\n  </tr>\n  <tr>\n    <td> </td>\n    <td> musMus6</td>\n  </tr>\n  <tr>\n    <td> </td>\n    <td> musMus7</td>\n  </tr>\n  <tr>\n    <td> </td>\n    <td> musMus8</td>\n  </tr>\n  <tr>\n    <td> galGal2</td>\n    <td> danRer2</td>\n  </tr>\n  <tr>\n    <td> </td>\n    <td> hg16</td>\n  </tr>\n  <tr>\n    <td> </td>\n    <td> hg17</td>\n  </tr>\n  <tr>\n    <td> </td>\n    <td> hg18</td>\n  </tr>\n  <tr>\n    <td> </td>\n    <td> musMus6</td>\n  </tr>\n  <tr>\n    <td> </td>\n    <td> musMus7</td>\n  </tr>\n  <tr>\n    <td> </td>\n    <td> musMus8</td>\n  </tr>\n  <tr>\n    <td> </td>\n    <td> monDom1</td>\n  </tr>\n  <tr>\n    <td> </td>\n    <td> ratNor4</td>\n  </tr>\n  <tr>\n    <td> </td>\n    <td> tetNig1</td>\n  </tr>\n  <tr>\n    <td> </td>\n    <td> xenTro1</td>\n  </tr>\n  <tr>\n    <td> hg16</td>\n    <td> musMus3</td>\n  </tr>\n  <tr>\n    <td> </td>\n    <td> mm4</td>\n  </tr>\n  <tr>\n    <td> </td>\n    <td> musMus6</td>\n  </tr>\n  <tr>\n    <td> </td>\n    <td> panTro1</td>\n  </tr>\n  <tr>\n    <td> </td>\n    <td> ratNor3</td>\n  </tr>\n  <tr>\n    <td> hg17</td>\n    <td> bosTau1</td>\n  </tr>\n  <tr>\n    <td> </td>\n    <td> bosTau2</td>\n  </tr>\n  <tr>\n    <td> </td>\n    <td> canFam1</td>\n  </tr>\n  <tr>\n    <td> </td>\n    <td> canFam2</td>\n  </tr>\n  <tr>\n    <td> </td>\n    <td> danRer1</td>\n  </tr>\n  <tr>\n    <td> </td>\n    <td> danRer2</td>\n  </tr>\n  <tr>\n    <td> </td>\n    <td> danRer3</td>\n  </tr>\n  <tr>\n    <td> </td>\n    <td> fr1</td>\n  </tr>\n  <tr>\n    <td> </td>\n    <td> galGal2</td>\n  </tr>\n  <tr>\n    <td> </td>\n    <td> musMus5</td>\n  </tr>\n  <tr>\n    <td> </td>\n    <td> musMus6</td>\n  </tr>\n  <tr>\n    <td> </td>\n    <td> musMus7</td>\n  </tr>\n  <tr>\n    <td> </td>\n    <td> monDom1</td>\n  </tr>\n  <tr>\n    <td> </td>\n    <td> panTro1</td>\n  </tr>\n  <tr>\n    <td> </td>\n    <td> rheMac1</td>\n  </tr>\n  <tr>\n    <td> </td>\n    <td> rheMac2</td>\n  </tr>\n  <tr>\n    <td> </td>\n    <td> ratNor3</td>\n  </tr>\n  <tr>\n    <td> </td>\n    <td> tetNig1</td>\n  </tr>\n  <tr>\n    <td> hg18</td>\n    <td> bosTau2</td>\n  </tr>\n  <tr>\n    <td> </td>\n    <td> canFam2</td>\n  </tr>\n  <tr>\n    <td> </td>\n    <td> danRer3</td>\n  </tr>\n  <tr>\n    <td> </td>\n    <td> danRer4</td>\n  </tr>\n  <tr>\n    <td> </td>\n    <td> fr1</td>\n  </tr>\n  <tr>\n    <td> </td>\n    <td> galGal2</td>\n  </tr>\n  <tr>\n    <td> </td>\n    <td> musMus7</td>\n  </tr>\n  <tr>\n    <td> </td>\n    <td> musMus8</td>\n  </tr>\n  <tr>\n    <td> </td>\n    <td> panTro1</td>\n  </tr>\n  <tr>\n    <td> </td>\n    <td> rheMac2</td>\n  </tr>\n  <tr>\n    <td> </td>\n    <td> ratNor4</td>\n  </tr>\n  <tr>\n    <td> </td>\n    <td> tetNig1</td>\n  </tr>\n  <tr>\n    <td> </td>\n    <td> xenTro1</td>\n  </tr>\n  <tr>\n    <td> musMus6</td>\n    <td> bosTau1</td>\n  </tr>\n  <tr>\n    <td> </td>\n    <td> canFam1</td>\n  </tr>\n  <tr>\n    <td> </td>\n    <td> danRer2</td>\n  </tr>\n  <tr>\n    <td> </td>\n    <td> fr1</td>\n  </tr>\n  <tr>\n    <td> </td>\n    <td> galGal2</td>\n  </tr>\n  <tr>\n    <td> </td>\n    <td> hg16</td>\n  </tr>\n  <tr>\n    <td> </td>\n    <td> hg17</td>\n  </tr>\n  <tr>\n    <td> </td>\n    <td> monDom1</td>\n  </tr>\n  <tr>\n    <td> </td>\n    <td> panTro1</td>\n  </tr>\n  <tr>\n    <td> </td>\n    <td> ratNor3</td>\n  </tr>\n  <tr>\n    <td> </td>\n    <td> tetNig1</td>\n  </tr>\n  <tr>\n    <td> </td>\n    <td> xenTro1</td>\n  </tr>\n  <tr>\n    <td> musMus7</td>\n    <td> bosTau2</td>\n  </tr>\n  <tr>\n    <td> </td>\n    <td> canFam2</td>\n  </tr>\n  <tr>\n    <td> </td>\n    <td> danRer3</td>\n  </tr>\n  <tr>\n    <td> </td>\n    <td> fr1</td>\n  </tr>\n  <tr>\n    <td> </td>\n    <td> galGal2</td>\n  </tr>\n  <tr>\n    <td> </td>\n    <td> hg17</td>\n  </tr>\n  <tr>\n    <td> </td>\n    <td> hg18</td>\n  </tr>\n  <tr>\n    <td> </td>\n    <td> panTro1</td>\n  </tr>\n  <tr>\n    <td> </td>\n    <td> rheMac1</td>\n  </tr>\n  <tr>\n    <td> </td>\n    <td> ratNor3</td>\n  </tr>\n  <tr>\n    <td> </td>\n    <td> tetNig1</td>\n  </tr>\n  <tr>\n    <td> </td>\n    <td> xenTro1</td>\n  </tr>\n  <tr>\n    <td> musMus8</td>\n    <td> bosTau2</td>\n  </tr>\n  <tr>\n    <td> </td>\n    <td> canFam2</td>\n  </tr>\n  <tr>\n    <td> </td>\n    <td> danRer3</td>\n  </tr>\n  <tr>\n    <td> </td>\n    <td> danRer4</td>\n  </tr>\n  <tr>\n    <td> </td>\n    <td> fr1</td>\n  </tr>\n  <tr>\n    <td> </td>\n    <td> galGal2</td>\n  </tr>\n  <tr>\n    <td> </td>\n    <td> hg17</td>\n  </tr>\n  <tr>\n    <td> </td>\n    <td> hg18</td>\n  </tr>\n  <tr>\n    <td> </td>\n    <td> monDom4</td>\n  </tr>\n  <tr>\n    <td> </td>\n    <td> panTro1</td>\n  </tr>\n  <tr>\n    <td> </td>\n    <td> rheMac2</td>\n  </tr>\n  <tr>\n    <td> </td>\n    <td> ratNor4</td>\n  </tr>\n  <tr>\n    <td> </td>\n    <td> tetNig1</td>\n  </tr>\n  <tr>\n    <td> </td>\n    <td> xenTro1</td>\n  </tr>\n  <tr>\n    <td> </td>\n    <td> xenTro2</td>\n  </tr>\n  <tr>\n    <td> panTro1</td>\n    <td> hg16</td>\n  </tr>\n  <tr>\n    <td> </td>\n    <td> hg18</td>\n  </tr>\n  <tr>\n    <td> </td>\n    <td> musMus6</td>\n  </tr>\n  <tr>\n    <td> </td>\n    <td> musMus7</td>\n  </tr>\n  <tr>\n    <td> </td>\n    <td> musMus8</td>\n  </tr>\n  <tr>\n    <td> rheMac2</td>\n    <td> hg18</td>\n  </tr>\n  <tr>\n    <td> </td>\n    <td> musMus8</td>\n  </tr>\n  <tr>\n    <td> </td>\n    <td> ratNor4</td>\n  </tr>\n  <tr>\n    <td> ratNor3</td>\n    <td> hg18</td>\n  </tr>\n  <tr>\n    <td> </td>\n    <td> musMus8</td>\n  </tr>\n  <tr>\n    <td> </td>\n    <td> ratNor4</td>\n  </tr>\n  <tr>\n    <td> ratNor4</td>\n    <td> hg18</td>\n  </tr>\n  <tr>\n    <td> </td>\n    <td> musMus8</td>\n  </tr>\n  <tr>\n    <td> </td>\n    <td> ratNor4</td>\n  </tr>\n  <tr>\n    <td> tetNig1</td>\n    <td> danRer3</td>\n  </tr>\n  <tr>\n    <td> </td>\n    <td> danRer4</td>\n  </tr>\n  <tr>\n    <td> </td>\n    <td> fr1</td>\n  </tr>\n  <tr>\n    <td> </td>\n    <td> hg17</td>\n  </tr>\n  <tr>\n    <td> </td>\n    <td> hg18</td>\n  </tr>\n  <tr>\n    <td> </td>\n    <td> musMus6</td>\n  </tr>\n  <tr>\n    <td> </td>\n    <td> musMus7</td>\n  </tr>\n  <tr>\n    <td> </td>\n    <td> musMus8</td>\n  </tr>\n</table>\n<p>4 multiZ alignments are available in Galaxy:</p>\n<ul>\n<li>hg17-panTro1-musMus5-ratNor3-canFam1-galGal2-fugRub1-danRer1</li>\n<li>hg18-panTro1-bosTau2-rheMac2-musMus8-ratNor4-canFam2-echTel1-loxAfr1-oryCun1-danRer3-monDom4-dasNov1-galGal2-fr1-tetNig1-xenTro1</li>\n<li>hg18-panTro2-rheMac2-musMus8-canFam2</li>\n<li>hg18-panTro2-rheMac2</li>\n</ul>\n"}},"context":{}}