{"hash":"49d9aebfc2ce77342c0ce224e1cb2c1a248b7103","data":{"article":{"id":"a4b0fb2cabe63baf6c6340701eccee2a","title":"Use the power of pandas / numpy to transform tabular datasets on UseGalaxy.eu","tease":"Drop or duplicate given rows or columns from a tabular dataset, filter rows or columns on their properties, replace or transform table elements, ...","category":"blog","date":"2019-10-23","days":null,"contact":"","contact_url":"","authors":"European Galaxy Team","location":"","location_url":"","source_blog":"UseGalaxy.eu","source_blog_url":"https://galaxyproject.eu/freiburg/news","skip_title_render":null,"redirect":"","links":[],"image":"","images":{},"external_url":"https://galaxyproject.eu/posts/2019/10/23/pandas-in-galaxy/","content":"\n"}},"context":{}}