{"hash":"f696d459c27618375ae9beff9077a6039192ee4e","data":{"article":{"id":"e1fa26f2196b73303f78e91243f04aa2","title":"DRS, long-read-sequencing, proteomics and more - An update to recent COVID-19 workflow developments","tease":"Open Data Infrastructures to tackle COVID-19 pandemic","category":"events","date":"2021-02-24","days":1,"contact":"Wolfgang Maier, Nathan Roach, Pratik Jagtap, Subina Mehta","contact_url":"","fileInfo":{"path":"build/content-md/events/2021-02-elixir-webinar-6/index.md"},"authors":"","location":"2nd Galaxy-ELIXIR webinar series, Online, Europe","location_url":"https://elixir-europe.org/events/2nd-galaxy-elixir-webinar-series","source_blog":"","source_blog_url":"","skip_title_render":null,"redirect":"","autotoc":null,"links":[{"url":"https://docs.google.com/presentation/d/1wcf1rkui8MZurMatpiJiWyt-cjkhIkO2Cx2lHlpTZE8","text":"Slides"},{"url":"https://youtu.be/HCNNUSlL73k","text":"Video"}],"image":"","images":{},"external_url":"https://elixir-europe.org/events/2nd-galaxy-elixir-webinar-series#session5","content":"\n"}},"context":{}}