{"hash":"fe50d2d58b71effa03c01b08cdaab48b91e9d3d3","data":{"article":{"id":"9ec16daa6600d5bba18ba2ff7b886bad","title":"TIaaS Queue Status","tease":"using UseGalaxy.eu’s Training infrastructure as a Service (TIaaS).","category":"news","date":"2019-06-17","days":null,"contact":"","contact_url":"","authors":"","location":"","location_url":"","source_blog":"","source_blog_url":"","skip_title_render":null,"links":[],"image":"","images":{},"external_url":"https://galaxyproject.eu/posts/2019/06/17/tiaas-queue/","content":"\n"}},"context":{}}