{"hash":"eaf962330836a104724e8b210d95933603316eda","data":{"article":{"id":"ed40b2c77622eed1549dea12a54ae1c1","title":"GCCBOSC 2018","tease":"GCC2018 and BOSC 2018 are joining forces in 2018","category":"events","date":"2018-06-25","days":6,"contact":"Organizers","contact_url":"","authors":"","location":"Reed College, Portland, Oregon, United States","location_url":"/events/gccbosc2018/venue/","source_blog":"","source_blog_url":"","skip_title_render":null,"redirect":"","links":[],"image":"/images/logos/gcc-bosc-2018-banner.png","images":{},"external_url":"https://gccbosc2018.sched.com","content":"\n"}},"context":{}}