{"hash":"413b95c96e3c2a1187afbfe2a34414202ea5b44f","data":{"article":{"id":"d3aef0df43e28c928ed0fd9da45bbea7","title":"GalaxyNL Meeting 2021","tease":"Gathering the Dutch Galaxy Community","category":"events","date":"2021-05-28","days":1,"contact":"Saskia Hiltemann","contact_url":"","authors":"","location":"Online, The Netherlands","location_url":"","source_blog":"","source_blog_url":"","skip_title_render":null,"links":[],"image":"/src/images/logos/galaxy-nl-big.png","images":{},"external_url":"https://docs.google.com/document/d/1irLt2gtm-iNdgDZqybUpj7g39zkf5qaDkGW4-wW31YQ/edit","content":"\n"}},"context":{}}