{"hash":"91d4a83f9855c194893a1f5e294057505b0cd33d","data":{"article":{"id":"953eb6b949e43d51a1c9e7da7d3c4bdc","title":"Gateways 2018","tease":"The 13th Gateway Computing Environments Conference (formerly GCE)","category":"events","date":"2018-09-25","days":3,"contact":"Katherine Lawrence","contact_url":"","authors":"","location":"University of Texas, Austin, Texas, United States","location_url":"https://sciencegateways.org/web/gateways2018/about","source_blog":"","source_blog_url":"","skip_title_render":null,"links":[],"image":"","images":{},"external_url":"https://sciencegateways.org/web/gateways2018","content":"\n"}},"context":{}}