{"hash":"49d9aebfc2ce77342c0ce224e1cb2c1a248b7103","data":{"article":{"id":"f8fd7ad23f83ea2a05373338692dcb6c","title":"Galaxy R Markdown Tools","tease":"Using R Markdown as a framework to develop Galaxy tools","category":"blog","date":"2018-01-08","days":null,"contact":"","contact_url":"","authors":"Ming Chen","location":"","location_url":"","source_blog":"Staton Lab","source_blog_url":"","skip_title_render":null,"redirect":"","links":[],"image":"","images":{},"external_url":"https://github.com/statonlab/galaxy-r-markdown-tools","content":"\n"}},"context":{}}