{"hash":"4f66c62fb6940f4cd6ecf5e4a1e2d62361ec5ff4","data":{"article":{"id":"32f7ed5e7d1ac29ad2d8e8e8f1a9aafa","title":"","tease":"","category":null,"date":null,"days":null,"contact":"","contact_url":"","fileInfo":{"path":"build/content-md/documents/presentations/gcc2013/index.md"},"authors":"","location":"","location_url":"","source_blog":"","source_blog_url":"","skip_title_render":null,"redirect":"","autotoc":null,"links":[],"image":"","images":{},"external_url":"","content":"<p>Presentations given at <a href=\"/events/gcc2013/\">GCC2013</a>.  See also <a href=\"/events/gcc2013/training-day/\">the Training Day page</a>.</p>\n<p>PLACEHOLDER_ATTACH_LIST</p>\n"}},"context":{}}