{"hash":"f696d459c27618375ae9beff9077a6039192ee4e","data":{"article":{"id":"31f169b9d340b95bb311be4418766d74","title":"ELIXIR and Galaxy Project","tease":"a high level overview of the Galaxy Project - what it is, what it does and how to start using it. And the Elixir Galaxy and currently forming Galaxy Czech communities","category":"events","date":"2021-04-16","days":1,"contact":"Martin Čech","contact_url":"","fileInfo":{"path":"build/content-md/events/2021-04-elixir-cz/index.md"},"authors":"","location":"ELIXIR CZ, Online, Czech Republic","location_url":"https://www.elixir-czech.cz/events","source_blog":"","source_blog_url":"","skip_title_render":null,"redirect":"","autotoc":null,"links":[{"url":"http://bit.ly/galaxy_coffee","text":"Slides"}],"image":"","images":{},"external_url":"https://www.elixir-czech.cz/events/elixir-cz-friday-coffee-16-april-2021","content":"\n"}},"context":{}}