{"hash":"ef8aba8bb8a02457efb168ecda8caf9311205534","data":{"platform":{"id":"423e1aa2ae733441f3f4b3fba2f2850b","title":"Nectar Cloud","url":"https://nectar.org.au/research-cloud/","image":"/src/images/logos/nectar-square-400.png","images":{},"platforms":[{"platform_group":"academic-cloud","platform_url":"https://nectar.org.au/research-cloud/","platform_text":"Nectar Cloud"}],"scope":"general","summary":"Set up a Galaxy server on Australia's Nectar research cloud.","comments":["Nectar based Galaxy instances can be easily started from CloudLaunch.  They are based on the Genomics Virtual Laboratory (GVL)."],"user_support":["[Launching a Personal GVL Server on the NeCTAR Research Cloud](https://melbournebioinformatics.github.io/MelBioInf_docs/tutorials/gvl_launch/gvl_launch/)"],"pub_libraries":["GVL"],"quotas":[],"citations":[],"sponsors":["Melbourne Bioinformatics and the Australian Research Data Commons."]}},"context":{}}