{"hash":"c32ecfdb33b075b0057598b5b9118f3554a398cf","data":{"article":{"id":"4afcba6419bed91c587a9242c7962b32","title":"Sci User Guild for Running Galaxy","tease":"","image":"","images":{},"category":null,"contact":"","date":null,"content":"<p><a href=\"http://wiki.galaxyproject.org/support/\" target=\"_blank\" rel=\"noopener noreferrer\">Back to Support Hub</a></p>\n<h1 id=\"scientific-user-guide-to-running-a-personal-galaxy-server\"><a href=\"#scientific-user-guide-to-running-a-personal-galaxy-server\" aria-hidden=\"true\"><span class=\"icon icon-link\"></span></a>Scientific user guide to running a personal Galaxy server</h1>\n<p><strong> COMMING SOON! </strong></p>\n"}},"context":{}}