{"hash":"f696d459c27618375ae9beff9077a6039192ee4e","data":{"article":{"id":"67d295ae34192fc47e4195cfe60b214a","title":"Computer Scientist","tease":"","category":"careers","date":"2021-07-13","days":null,"contact":"","contact_url":"","fileInfo":{"path":"build/content-md/careers/2021-07-fda/index.md"},"authors":"","location":"Food and Drug Administration (FDA), Center for Food Safety and Applied Nutrition, College Park, Maryland, United States","location_url":"https://www.fda.gov/about-fda/fda-organization/center-food-safety-and-applied-nutrition-cfsan","source_blog":"","source_blog_url":"","skip_title_render":null,"redirect":"","autotoc":null,"links":[],"image":"/src/images/logos/fda-logo-wide.png","images":{},"external_url":"https://www.usajobs.gov/GetJob/ViewDetails/606850100","content":"\n"}},"context":{}}