{"hash":"a97cc003ab7b7b0128b2927bf289a961e571a0b8","data":{"article":{"id":"cac57c56cf73fa4a4a3db930314f8e3d","title":"Galaxy @ GOBLET 2020 AGM","tease":"Galaxy for learning, education, and training","category":"events","date":"2020-09-14","days":3,"contact":"Fotis Psomopoulos, Gareth Price","contact_url":"","authors":"","location":"Online, Sweden","location_url":"https://mygoblet.org/goblet-agm2020/","source_blog":"","source_blog_url":"","skip_title_render":null,"redirect":"","autotoc":null,"links":[],"image":"/src/images/logos/GobletLogo.png","images":{},"external_url":"","content":"<p>Galaxy is a member of <a href=\"https://mygoblet.org/\" target=\"_blank\" rel=\"noopener noreferrer\">GOBLET</a> and had two presentations at the 2020 GOBLET AGM</p>\n<ul>\n<li><a href=\"https://drive.google.com/file/d/1bnC7DZWWBF2B3jSKVm4o6ktHaN3Tr8cH/view?usp=sharing\" target=\"_blank\" rel=\"noopener noreferrer\">Delivering hands-on training for Machine Learning on omics data through Galaxy</a>, Fotis Psomopoulos, INAB, CERTH, Greece</li>\n<li><a href=\"https://drive.google.com/file/d/1dlTTuF8-wtu8mE2Lt45xK-96nS8ey1FF/view\" target=\"_blank\" rel=\"noopener noreferrer\">The use of the Remo Conference platform as a Workshop medium – experiences from BCC2020</a>, Gareth Price, QFAB, Australia</li>\n</ul>\n"}},"context":{}}