{"hash":"fe50d2d58b71effa03c01b08cdaab48b91e9d3d3","data":{"article":{"id":"10ad701ef10f8ef653bc28ec5a402488","title":"Online data analysis for biologists","tease":"Get a hands-on introduction to Galaxy, an online platform for data analysis","category":"events","date":"2020-11-12","days":1,"contact":"Simon Gladman","contact_url":"","authors":"","location":"Australian BioCommons, Online, Melbourne, Victoria, Australia","location_url":"","source_blog":"","source_blog_url":"","skip_title_render":null,"links":[],"image":"","images":{},"external_url":"https://www.eventbrite.com.au/e/online-data-analysis-for-biologists-november-2020-tickets-123259172503","content":"\n"}},"context":{}}